hippoformer/__init__.py
hippoformer/hippoformer.py
hippoformer-0.0.15.dist-info/METADATA
hippoformer-0.0.15.dist-info/WHEEL
hippoformer-0.0.15.dist-info/licenses/LICENSE
hippoformer-0.0.15.dist-info/RECORD
