Metadata-Version: 2.4
Name: hippoformer
Version: 0.0.15
Summary: hippoformer
Project-URL: Homepage, https://pypi.org/project/hippoformer/
Project-URL: Repository, https://github.com/lucidrains/hippoformer
Author-email: Phil Wang <lucidrains@gmail.com>
License: MIT License
License-File: LICENSE
Keywords: artificial intelligence,deep learning,hippocampus,memory
Classifier: Development Status :: 4 - Beta
Classifier: Intended Audience :: Developers
Classifier: License :: OSI Approved :: MIT License
Classifier: Programming Language :: Python :: 3.9
Classifier: Topic :: Scientific/Engineering :: Artificial Intelligence
Requires-Python: >=3.9
Requires-Dist: assoc-scan
Requires-Dist: beartype
Requires-Dist: einops>=0.8.1
Requires-Dist: einx>=0.3.0
Requires-Dist: torch>=2.4
Requires-Dist: x-mlps-pytorch
Provides-Extra: examples
Provides-Extra: test
Requires-Dist: pytest; extra == 'test'
